topsis/__init__.py
topsis/__main__.py
Topsis_Arnav_101953016-1.0.0.dist-info/LICENSE
Topsis_Arnav_101953016-1.0.0.dist-info/METADATA
Topsis_Arnav_101953016-1.0.0.dist-info/WHEEL
Topsis_Arnav_101953016-1.0.0.dist-info/entry_points.txt
Topsis_Arnav_101953016-1.0.0.dist-info/top_level.txt
Topsis_Arnav_101953016-1.0.0.dist-info/RECORD
